{
  "multipart": [
    {
      "apply": {
        "model": "kamen_rider_weapon_craft:block/helheimvine"
      },
      "when": {
        "north": "true"
      }
    },
    {
      "apply": {
        "model": "kamen_rider_weapon_craft:block/helheimvine"
      },
      "when": {
        "east": "false",
        "north": "false",
        "south": "false",
        "up": "false",
        "west": "false"
      }
    },
    {
      "apply": {
        "model": "kamen_rider_weapon_craft:block/helheimvine",
        "uvlock": true,
        "y": 90
      },
      "when": {
        "east": "true"
      }
    },
    {
      "apply": {
        "model": "kamen_rider_weapon_craft:block/helheimvine",
        "uvlock": true,
        "y": 90
      },
      "when": {
        "east": "false",
        "north": "false",
        "south": "false",
        "up": "false",
        "west": "false"
      }
    },
    {
      "apply": {
        "model": "kamen_rider_weapon_craft:block/helheimvine",
        "uvlock": true,
        "y": 180
      },
      "when": {
        "south": "true"
      }
    },
    {
      "apply": {
        "model": "kamen_rider_weapon_craft:block/helheimvine",
        "uvlock": true,
        "y": 180
      },
      "when": {
        "east": "false",
        "north": "false",
        "south": "false",
        "up": "false",
        "west": "false"
      }
    },
    {
      "apply": {
        "model": "kamen_rider_weapon_craft:block/helheimvine",
        "uvlock": true,
        "y": 270
      },
      "when": {
        "west": "true"
      }
    },
    {
      "apply": {
        "model": "kamen_rider_weapon_craft:block/helheimvine",
        "uvlock": true,
        "y": 270
      },
      "when": {
        "east": "false",
        "north": "false",
        "south": "false",
        "up": "false",
        "west": "false"
      }
    },
    {
      "apply": {
        "model": "kamen_rider_weapon_craft:block/helheimvine",
        "uvlock": true,
        "x": 270
      },
      "when": {
        "up": "true"
      }
    },
    {
      "apply": {
        "model": "kamen_rider_weapon_craft:block/helheimvine",
        "uvlock": true,
        "x": 270
      },
      "when": {
        "east": "false",
        "north": "false",
        "south": "false",
        "up": "false",
        "west": "false"
      }
    }
  ]
}